odoo/addons/delivery_carrier_global_manifest/README.rst
odoo/addons/delivery_carrier_global_manifest/__init__.py
odoo/addons/delivery_carrier_global_manifest/__manifest__.py
odoo/addons/delivery_carrier_global_manifest/i18n/delivery_carrier_global_manifest.pot
odoo/addons/delivery_carrier_global_manifest/i18n/es.po
odoo/addons/delivery_carrier_global_manifest/i18n/it.po
odoo/addons/delivery_carrier_global_manifest/models/__init__.py
odoo/addons/delivery_carrier_global_manifest/models/delivery_carrier.py
odoo/addons/delivery_carrier_global_manifest/readme/CONFIGURE.md
odoo/addons/delivery_carrier_global_manifest/readme/CONTRIBUTORS.md
odoo/addons/delivery_carrier_global_manifest/readme/DESCRIPTION.md
odoo/addons/delivery_carrier_global_manifest/readme/USAGE.md
odoo/addons/delivery_carrier_global_manifest/report/manifest_wizard_view.xml
odoo/addons/delivery_carrier_global_manifest/static/description/icon.png
odoo/addons/delivery_carrier_global_manifest/static/description/icon.svg
odoo/addons/delivery_carrier_global_manifest/static/description/index.html
odoo/addons/delivery_carrier_global_manifest/tests/__init__.py
odoo/addons/delivery_carrier_global_manifest/tests/test_delivery_carrier_global_manifest.py
odoo/addons/delivery_carrier_global_manifest/views/delivery_carrier_view.xml
odoo/addons/delivery_carrier_global_manifest/wizards/__init__.py
odoo/addons/delivery_carrier_global_manifest/wizards/manifest_wizard.py
odoo/addons/delivery_carrier_global_manifest/wizards/manifest_wizard_view.xml
odoo_addon_delivery_carrier_global_manifest-17.0.1.0.0.3.dist-info/METADATA
odoo_addon_delivery_carrier_global_manifest-17.0.1.0.0.3.dist-info/WHEEL
odoo_addon_delivery_carrier_global_manifest-17.0.1.0.0.3.dist-info/top_level.txt
odoo_addon_delivery_carrier_global_manifest-17.0.1.0.0.3.dist-info/RECORD
